django_scoped_permissions/__init__.py
django_scoped_permissions/admin.py
django_scoped_permissions/backends.py
django_scoped_permissions/core.py
django_scoped_permissions/decorators.py
django_scoped_permissions/graphql.py
django_scoped_permissions/graphql_util.py
django_scoped_permissions/guards.py
django_scoped_permissions/models.py
django_scoped_permissions/schema.py
django_scoped_permissions/urls.py
django_scoped_permissions/util.py
django_scoped_permissions/wsgi.py
django_scoped_permissions/__pycache__/__init__.cpython-38.pyc
django_scoped_permissions/__pycache__/__init__.cpython-39.pyc
django_scoped_permissions/__pycache__/util.cpython-38.pyc
django_scoped_permissions/__pycache__/util.cpython-39.pyc
django_scoped_permissions/migrations/0001_initial.py
django_scoped_permissions/migrations/0002_scopedpermissiongroup.py
django_scoped_permissions/migrations/__init__.py
django_scoped_permissions/tests/__init__.py
django_scoped_permissions/tests/factories.py
django_scoped_permissions/tests/models.py
django_scoped_permissions/tests/schema.py
django_scoped_permissions/tests/test_core.py
django_scoped_permissions/tests/test_decorators.py
django_scoped_permissions/tests/test_graphql.py
django_scoped_permissions/tests/test_graphql_util.py
django_scoped_permissions/tests/test_guards.py
django_scoped_permissions/tests/test_models.py
django_scoped_permissions/tests/test_permissions.py
django_scoped_permissions/tests/urls.py
django_scoped_permissions/tests/migrations/0001_initial.py
django_scoped_permissions/tests/migrations/0002_auto_20201219_2245.py
django_scoped_permissions/tests/migrations/0003_auto_20210202_0853.py
django_scoped_permissions/tests/migrations/__init__.py
django_scoped_permissions-0.1.8.dist-info/METADATA
django_scoped_permissions-0.1.8.dist-info/WHEEL
django_scoped_permissions-0.1.8.dist-info/top_level.txt
django_scoped_permissions-0.1.8.dist-info/RECORD
