Metadata-Version: 2.1
Name: django-scoped-permissions
Version: 0.1.8
Summary: Scoped permission system for Django
Home-page: https://github.com/Ur-Solutions/django_scoped_permissions
Author: Tormod Haugland, Magnus Buvarp
Author-email: tormod.haugland@gmail.com, magnus.buvarp@gmail.com
License: UNKNOWN
Platform: UNKNOWN
Classifier: Programming Language :: Python :: 3
Classifier: License :: OSI Approved :: MIT License
Classifier: Operating System :: OS Independent
Requires-Dist: django >=2.0.0
Requires-Dist: pydash >=4.0.0
